MUSAN/__init__.py
MUSAN/_version.py
MUSAN/data/all.txt
MUSAN/data/background_noise.txt
MUSAN/data/music.txt
MUSAN/data/noise.txt
MUSAN/data/speech.txt
pyannote.db.musan-1.0.dist-info/LICENSE
pyannote.db.musan-1.0.dist-info/METADATA
pyannote.db.musan-1.0.dist-info/WHEEL
pyannote.db.musan-1.0.dist-info/entry_points.txt
pyannote.db.musan-1.0.dist-info/top_level.txt
pyannote.db.musan-1.0.dist-info/RECORD
